Workbook

Sheet 总表（人力）
A1: 序号 | B1: 事项 | C1: Q1
A2: 1 | B2: 部门人员投入本部门项目人力成本总计 | C2: ==项目工时汇总!F57 | D2: ==C2/E2 | E2: ==C2+C3
A3: 2 | B3: 外部门投入本部门项目人力成本总计 | C3: ==项目工时汇总!F58 | D3: ==C3/E2
A4: 3 | B4: 部门人员投入本部门日志总计 | C4: ==部门日志汇总!C15 | D4: ==C4/E4 | E4: ==C4+C6
A5: 4 | B5: 其中 | C5: 44269.97
A6: 5 | B6: 外部门投入本部门日志总计 | C6: ==部门日志汇总!D15 | D6: ==C6/E4
A7: 6 | B7: 部门人员投入非本部门项目人力成本总计 | C7: ==项目工时汇总!F59 | D7: ==C7/(C2+C4)
B11: 部门人力成本小计 | C11: ==C2+C4+C7 | D11: ==C11/E11 | E11: ==C11+C12
B12: 外部门投入本部门事务成本小计 | C12: ==C3+C6 | D12: ==C12/E11

Sheet 部门日志汇总
A2: 日志任务名称 | B2: 日志工时 | C2: 日志工时金额（部门内） | D2: 日志工时金额（部门外）
A3: 部门管理 | B3: 42.7 | C3: 56579.08 | D3: 0
A4: 市场营销 | B4: 26.6 | C4: 28514.71 | D4: 0
A5: 乘云会客厅 | B5: 16.1 | C5: 17151.43 | D5: 0
A6: 省级拓展 | B6: 9.5 | C6: 14292.7 | D6: 0
A7: 行业协会商会 | B7: 13.85 | C7: 12399.98 | D7: 0
A8: 场景探索 | B8: 8.9 | C8: 10523.34 | D8: 0
A9: AI数字社区 | B9: 7 | C9: 9376.13 | D9: 0
A10: 新就业群体 | B10: 8.6 | C10: 8701.31 | D10: 0
A11: 一张图 | B11: 7.7 | C11: 7375.22 | D11: 258.75
A12: 内部交流 | B12: 7 | C12: 7044.79 | D12: 0
A13: 两个覆盖 | B13: 4.8 | C13: 5113.74 | D13: 0
A14: 人民建议征集 | B14: 1 | C14: 1044.84 | D14: 0
B15: 总计 | C15: ==SUM(C3:C14) | D15: ==SUM(D3:D14)

Sheet 项目工时汇总
A1: 项目编号 | B1: 统一项目名称 | C1: 总工时 | D1: 总工时金额 | F1: 部门内人员 | H1: 外部门人员
E2: 平均工时金额 | F2: 工时 | G2: 工时金额 | H2: 工时 | I2: 工时金额 | J2: 项目归属部门 | K2: 项目阶段
A3: TB12024068 | B3: 天府新区公共服务码二期项目 | C3: ==H3+F3 | D3: ==I3+G3 | E3: ==D3/C3 | F3: 2 | G3: 1500 | H3: 0 | I3: 0 | J3: 非 | K3: 商机
A4: TB12025013 | B4: 东部新区智能社工项目 | C4: ==H4+F4 | D4: ==I4+G4 | E4: ==D4/C4 | F4: 21.5 | G4: 21643.53 | H4: 10.5 | I4: 11511.42 | J4: 是 | K4: 商机
A5: TB12025020 | B5: 锦江社区智能助手项目 | C5: ==H5+F5 | D5: ==I5+G5 | E5: ==D5/C5 | F5: 14 | G5: 10866.5 | H5: 0 | I5: 0 | J5: 是 | K5: 商机
A6: TB12025024 | B6: 四川省委社工部一体化项目申报备案及课题调研 | C6: ==H6+F6 | D6: ==I6+G6 | E6: ==D6/C6 | F6: 3.5 | G6: 3162.5 | H6: 0 | I6: 0 | J6: 是 | K6: 商机
A7: TB12026001 | B7: 2026年崇州激励资金项目 | C7: ==H7+F7 | D7: ==I7+G7 | E7: ==D7/C7 | F7: 37 | G7: 27765.33 | H7: 0 | I7: 0 | J7: 是 | K7: 商机
A8: TB12026002 | B8: 四川省委社工部热点信息 | C8: ==H8+F8 | D8: ==I8+G8 | E8: ==D8/C8 | F8: 22.5 | G8: 21600.99 | H8: 0 | I8: 0 | J8: 是 | K8: 商机
A9: TB202602001 | B9: 攀枝花市东区智慧教育新型基础设施建设项目第三期（一标段） | C9: ==H9+F9 | D9: ==I9+G9 | E9: ==D9/C9 | F9: 4 | G9: 3937.52 | H9: 0 | I9: 0 | J9: 非 | K9: 商机
A10: TB202602004 | B10: 温江政务应用程序的集约化整合服务 | C10: ==H10+F10 | D10: ==I10+G10 | E10: ==D10/C10 | F10: 14.5 | G10: 10757.62 | H10: 0.5 | I10: 431.25 | J10: 是 | K10: 商机
A11: TB202602005 | B11: 2026年崇州社会工作部智慧化 | C11: ==H11+F11 | D11: ==I11+G11 | E11: ==D11/C11 | F11: 45.8 | G11: 46400.51 | H11: 27 | I11: 24384.92 | J11: 是 | K11: 商机
A12: TB202602006 | B12: 2026年大邑社会工作部智慧化 | C12: ==H12+F12 | D12: ==I12+G12 | E12: ==D12/C12 | F12: 2 | G12: 1221.22 | H12: 0 | I12: 0 | J12: 是 | K12: 商机
A13: TB202602008 | B13: 2026年大邑激励资金项目 | C13: ==H13+F13 | D13: ==I13+G13 | E13: ==D13/C13 | F13: 3 | G13: 1831.83 | H13: 0 | I13: 0 | J13: 是 | K13: 商机
A14: TB202602010 | B14: 2026年蒲江社会工作部智慧化 | C14: ==H14+F14 | D14: ==I14+G14 | E14: ==D14/C14 | F14: 8 | G14: 5342.82 | H14: 0 | I14: 0 | J14: 是 | K14: 商机
... A53: TP71152026001 | B53: 龙泉驿数据支撑技术服务-垂直行业AI大模型项目 | C53: ==H53+F53 | D53: ==I53+G53 | E53: ==D53/C53 | F53: 3.6 | G53: 3291.36 | H53: 0 | I53: 0 | J53: 是 | K53: 交付
E57: 部门人员投入本部门项目人力成本总计 | F57: ==SUMIF(J3:J53,"是",G3:G53)
E58: 外部门投入本部门项目人力成本总计 | F58: ==SUM(I3:I53)
E59: 部门人员投入非本部门项目人力成本总计 | F59: ==SUMIF(J3:J53,"非",G3:G53)
E64: 210946.56

Sheet 原始-部门
A1: 部门日志明细汇总（超管）V2
A2: 数据源：日志管理-申请V2 执行时间：2026-04-01 16:26:47
A3: 日志部门名称 | B3: 日志任务名称 | C3: 日志工作内容 | D3: 日志工时 | E3: 日志工时金额 | F3: 流程状态 | G3: 填报人 | H3: 填报部门 | I3: 日期 | J3: 日志开始日期 | K3: 日志截止日期
A4: 社会工作业务部 | B4: 一张图 | C4: 技术可行性评估 | D4: 0.3 | E4: 258.75 | F4: 已结束 | G4: 熊禹 | H4: 交付管理中心 | I4: 46112 | J4: 46104 | K4: 46110
A5: 社会工作业务部 | B5: 内部交流 | C5: 内容指导 | D5: 0.5 | E5: 714.02 | F5: 未结束 | G5: 黄千偌 | H5: 社会工作业务部 | I5: 46111 | J5: 46104 | K5: 46110
A6: 社会工作业务部 | B6: 部门管理 | C6: 内部季度目标梳理 | D6: 1.5 | E6: 2142.05 | F6: 未结束 | G6: 黄千偌 | H6: 社会工作业务部 | I6: 46111 | J6: 46104 | K6: 46110
A7: 社会工作业务部 | B7: 部门管理 | C7: 成本管理办法思考、沟通、确认 | D7: 1 | E7: 1158.33 | F7: 未结束 | G7: 易云浩 | H7: 社会工作业务部 | I7: 46108 | J7: 46104 | K7: 46110
A8: 社会工作业务部 | B8: 部门管理 | C8: 第一季度绩效考核，第二季度绩效制定 | D8: 0.5 | E8: 579.17 | F8: 未结束 | G8: 易云浩 | H8: 社会工作业务部 | I8: 46108 | J8: 46104 | K8: 46110
A9: 社会工作业务部 | B9: 市场营销 | C9: 区县铺排情况同步售前 | D9: 0.2 | E9: 231.67 | F9: 未结束 | G9: 易云浩 | H9: 社会工作业务部 | I9: 46108 | J9: 46104 | K9: 46110
A10: 社会工作业务部 | B10: 乘云会客厅 | C10: 1、收集整理最后一家供应商报价内容，筛选3家报价确定控制价；2、根据要求准备报价函、拟邀供应商名单、比价文件、采购及上会审批表内容；3、视频内容脚本优化。 | D10: 2 | E10: 1994.7 | F10: 未结束 | G10: 郭霏 | H10: 社会工作业务部 | I10: 46113 | J10: 46104 | K10: 46110
A11: 社会工作业务部 | B11: 部门管理 | C11: 参加部门绩效沟通会议和项目沟通会议 | D11: 0.5 | E11: 357.96 | F11: 未结束 | G11: 王浩 | H11: 社会工作业务部 | I11: 46113 | J11: 46104 | K11: 46110
A12: 社会工作业务部 | B12: 部门管理 | C12: 公司绩效、部门Q2、过程内容审核 | D12: 3 | E12: 4284.09 | F12: 已结束 | G12: 黄千偌 | H12: 社会工作业务部 | I12: 46104 | J12: 46097 | K12: 46103
A13: 社会工作业务部 | B13: 两个覆盖 | C13: 1、按照与党支部沟通情况，修改方案；2、与一粒麦子、新空间等社会组织沟通合作可能； | D13: 1 | E13: 1158.33 | F13: 未结束 | G13: 易云浩 | H13: 社会工作业务部 | I13: 46101 | J13: 46097 | K13: 46103
A14: 社会工作业务部 | B14: 市场营销 | C14: 揭榜挂帅发文编写 | D14: 0.3 | E14: 347.5 | F14: 未结束 | G14: 易云浩 | H14: 社会工作业务部 | I14: 46101 | J14: 46097 | K14: 46103
A15: 社会工作业务部 | B15: 乘云会客厅 | C15: 1、与采购同事沟通，沟通目前公司两种采购流程需要的文件清单；2、沟通4家供应商，分别发布需求清单，收集整理3家报价，撰写询价函；3、撰写发布后筹备任务，整理内部会议沟通前筹备工作；4、内部动员会 | D15: 2.5 | E15: 2493.38 | F15: 未结束 | G15: 郭霏 | H15: 社会工作业务部 | I15: 46113 | J15: 46097 | K15: 46103
... A134: 社会工作业务部 | B134: 内部交流 | C134: 学习蓉会通产品资料和深度运营方案 | D134: 1.5 | E134: 1125 | F134: 已结束 | G134: 莫雷 | H134: 社会工作业务部 | I134: 46086 | J134: 46027 | K134: 46033

Sheet 原始表-商机
A1: 商机日志明细汇总（超管）V2
A2: 数据源：日志管理-申请V2,商机管理-台账V2 执行时间：2026-04-08 15:45:46
A3: 商机名称 | B3: 商机编号 | C3: 工时 | D3: 工时金额 | E3: 填报人
A4: 2026年蒲江社会工作部智慧化 | B4: TB202602010 | C4: 3 | D4: 1831.83 | E4: 熊偲吉
A5: 2026年崇州社会工作部智慧化 | B5: TB202602005 | C5: 2 | D5: 1221.22 | E5: 熊偲吉
A6: 2026年蒲江社会工作部智慧化 | B6: TB202602010 | C6: 0.2 | D6: 172.5 | E6: 褚骏涵
A7: 社区智能助手 | B7: TB202602021 | C7: 0.3 | D7: 347.5 | E7: 易云浩
A8: 社区智能助手 | B8: TB202602021 | C8: 5 | D8: 4312.5 | E8: 姚超
A9: 2026年大邑激励资金项目 | B9: TB202602008 | C9: 1 | D9: 610.61 | E9: 熊偲吉
A10: 2026年蒲江社会工作部智慧化 | B10: TB202602010 | C10: 3 | D10: 1831.83 | E10: 熊偲吉
A11: 2026年崇州激励资金项目 | B11: TB12026001 | C11: 1 | D11: 610.61 | E11: 熊偲吉
A12: 金控集团纪检项目 | B12: TB202603003 | C12: 1 | D12: 1428.03 | E12: 黄千偌
A13: 社区智能助手 | B13: TB202602021 | C13: 0.6 | D13: 695 | E13: 易云浩
A14: 郫都区2026年新就业服务项目 | B14: TB202603016 | C14: 1.5 | D14: 1368.18 | E14: 张涛
A15: 郫都行业商业协会运营项目 | B15: TB202603015 | C15: 1.5 | D15: 1368.18 | E15: 张涛
... A122: 锦江社区智能助手项目 | B122: TB12025020 | C122: 2 | D122: 1500 | E122: 莫雷

Sheet 原始表-项目
A2: 项目日志明细汇总（超管）V2
A3: 数据源：日志管理-申请V2,项目管理-台账V2 执行时间：2026-04-08 15:46:44
A4: 项目名称 | B4: 项目编号 | C4: 项目经理 | D4: 工时 | E4: 工时金额 | F4: 填报人
A5: 新都智慧社区平台 | B5: TP41132023024 | C5: 汪志炯 | D5: 1 | E5: 715.91 | F5: 史晓凡
A6: 东部新区智慧社区项目（蓝绸带社区） | B6: TP41132023224 | C6: 易云浩 | D6: 0.72 | E6: 515.46 | F6: 史晓凡
A7: 2024年—2025年天府市民云新都区特色门户服务采购项目 | B7: TP41142024043 | C7: 汪志炯 | D7: 0.28 | E7: 200.45 | F7: 史晓凡
A8: 郫都区智能社工项目 | B8: TP41112025045 | C8: 王添 | D8: 1 | E8: 997.35 | F8: 李成
A9: 成都高新区新就业群体参与食品安全监督等基层治理服务场景项目 | B9: TP41132025046 | C9: 王添 | D9: 1 | E9: 610.61 | F9: 王明珠
A10: 郫都区智能社工项目 | B10: TP41112025045 | C10: 王添 | D10: 0.5 | E10: 431.25 | F10: 冯凡
A11: 社工一体化平台项目 | B11: TP31102025027 | C11: 黄萍 | D11: 4 | E11: 3450 | F11: 冯凡
A12: 金牛区社会工作部“金牛提案”提质升级项目 | B12: TP41102025024 | C12: 褚骏涵 | D12: 0.4 | E12: 345 | F12: 褚骏涵
A13: 温江区人民建议征集与亲邻协商项目 | B13: TP41102025029 | C13: 褚骏涵 | D13: 2.3 | E13: 1983.75 | F13: 褚骏涵
A14: 双流区天府市民云服务项目（第六期）合同书 | B14: TP41112025002 | C14: 褚骏涵 | D14: 0.4 | E14: 345 | F14: 褚骏涵
A15: 2025年蒲江天府市民云门户 | B15: TP41132025023 | C15: 褚骏涵 | D15: 0.5 | E15: 431.25 | F15: 褚骏涵
A16: 龙泉驿区智慧蓉城特色服务优化提升运营项目 | B16: TP41112025034 | C16: 褚骏涵 | D16: 0.6 | E16: 517.5 | F16: 褚骏涵
... A510: 社工一体化平台项目 | B510: TP31102025027 | C510: 黄萍 | D510: 4 | E510: 3000 | F510: 王浩
